MANIFEST.in
pavement.py
paver-minilib.zip
setup.py
examples/PIRA001.cnv
pydap/__init__.py
pydap.handlers.cnv.egg-info/PKG-INFO
pydap.handlers.cnv.egg-info/SOURCES.txt
pydap.handlers.cnv.egg-info/dependency_links.txt
pydap.handlers.cnv.egg-info/entry_points.txt
pydap.handlers.cnv.egg-info/namespace_packages.txt
pydap.handlers.cnv.egg-info/not-zip-safe
pydap.handlers.cnv.egg-info/requires.txt
pydap.handlers.cnv.egg-info/top_level.txt
pydap/handlers/__init__.py
pydap/handlers/cnv/__init__.py