Metadata-Version: 1.1
Name: pydap.handlers.cnv
Version: 0.0.2
Summary: A CTD handler for Pydap
Home-page: http://
Author: Guilherme Castelao
Author-email: guilherme@castelao.net
License: MIT
Keywords: cnv ctd database opendap dods dap data science climate oceanography meteorology
Platform: UNKNOWN
Classifier: Development Status :: 3 - Alpha
Classifier: Environment :: Console
Classifier: Environment :: Web Environment
Classifier: Framework :: Paste
Classifier: Intended Audience :: Developers
Classifier: Intended Audience :: Science/Research
Classifier: License :: OSI Approved :: MIT License
Classifier: Operating System :: OS Independent
Classifier: Programming Language :: Python
Classifier: Topic :: Internet
Classifier: Topic :: Internet :: WWW/HTTP :: WSGI
Classifier: Topic :: Scientific/Engineering
Classifier: Topic :: Software Development :: Libraries :: Python Modules
